chck/__init__.py
chck/_modidx.py
chck/alls.py
chck/ares.py
chck/atyp.py
chck/biol.py
chck/bool.py
chck/call.py
chck/comp.py
chck/core.py
chck/dcls.py
chck/dict.py
chck/duck.py
chck/enum.py
chck/fref.py
chck/insp.py
chck/isad.py
chck/isan.py
chck/iscv.py
chck/isnp.py
chck/ispd.py
chck/issp.py
chck/iter.py
chck/itrs.py
chck/lens.py
chck/misc.py
chck/path.py
chck/pyty.py
chck/strs.py
chck/tgrd.py
chck/trch.py
chck/wrap.py
chck-0.0.75.dist-info/LICENSE
chck-0.0.75.dist-info/METADATA
chck-0.0.75.dist-info/WHEEL
chck-0.0.75.dist-info/entry_points.txt
chck-0.0.75.dist-info/top_level.txt
chck-0.0.75.dist-info/RECORD
