Metadata-Version: 2.1
Name: chck
Version: 0.0.75
Summary: chck
Home-page: https://github.com/dsm-72/chck
Author: dsm-72
Author-email: sumner.magruder@yale.edu
License: Apache Software License 2.0
Keywords: chck is question bool type guard typeguard check chck
Classifier: Development Status :: 4 - Beta
Classifier: Intended Audience :: Developers
Classifier: Natural Language :: English
Classifier: Programming Language :: Python :: 3.11
Classifier: License :: OSI Approved :: Apache Software License
Requires-Python: >=3.11
License-File: LICENSE
Requires-Dist: dref
Requires-Dist: quac
Provides-Extra: dev
